README.txt
mlsplit.py
setup.py
mlsplit.egg-info/PKG-INFO
mlsplit.egg-info/SOURCES.txt
mlsplit.egg-info/dependency_links.txt
mlsplit.egg-info/not-zip-safe
mlsplit.egg-info/top_level.txt
