Metadata-Version: 1.0
Name: mlsplit
Version: 0.1.2
Summary: Split Malayalam words into letters
Home-page: http://pypi.python.org/pypi/mlsplit
Author: Baiju M
Author-email: baiju.m.mail@gmail.com
License: GPLv3
Keywords: pypi console tools
Platform: UNKNOWN
Classifier: Development Status :: 4 - Beta
Classifier: Environment :: Console
Classifier: Intended Audience :: End Users/Desktop
Classifier: License :: OSI Approved :: GNU General Public License (GPL)
Classifier: Operating System :: OS Independent
Classifier: Programming Language :: Python
Classifier: Topic :: Utilities
